scrape_glosbe_dict/__init__.py
scrape_glosbe_dict/__main__.py
scrape_glosbe_dict/config.py
scrape_glosbe_dict/scrape_glosbe_dict.py
scrape_glosbe_dict-0.1.1.dist-info/entry_points.txt
scrape_glosbe_dict-0.1.1.dist-info/LICENSE
scrape_glosbe_dict-0.1.1.dist-info/WHEEL
scrape_glosbe_dict-0.1.1.dist-info/METADATA
scrape_glosbe_dict-0.1.1.dist-info/RECORD
