Metadata-Version: 2.1
Name: scrape-glosbe-dict
Version: 0.1.1
Summary: Scrape glosbe dicts given a head words file
Home-page: https://github.com/ffreemt/scrape-glosbe-dict
License: MIT
Author: ffreemt
Requires-Python: >=3.8.3,<4.0.0
Classifier: License :: OSI Approved :: MIT License
Classifier: Programming Language :: Python :: 3
Classifier: Programming Language :: Python :: 3.10
Classifier: Programming Language :: Python :: 3.9
Requires-Dist: cchardet (>=2.1.7,<3.0.0)
Requires-Dist: httpx (>=0.22.0,<0.23.0)
Requires-Dist: icecream (>=2.1.1,<3.0.0)
Requires-Dist: install (>=1.3.5,<2.0.0)
Requires-Dist: joblib (>=1.1.0,<2.0.0)
Requires-Dist: logzero (>=1.7.0,<2.0.0)
Requires-Dist: pydantic (>=1.9.0,<2.0.0)
Requires-Dist: pyquery (>=1.4.3,<2.0.0)
Requires-Dist: ratelimit (>=2.2.1,<3.0.0)
Requires-Dist: set-loglevel (>=0.1.1,<0.2.0)
Requires-Dist: tenacity (>=8.0.1,<9.0.0)
Requires-Dist: toml (>=0.10.2,<0.11.0)
Requires-Dist: tqdm (>=4.64.0,<5.0.0)
Requires-Dist: typer (>=0.4.1,<0.5.0)
Project-URL: Repository, https://github.com/ffreemt/scrape-glosbe-dict
